<annotation>
	<folder>uhk.fim.relayml</folder>
	<filename>image_638096484630082517.bmp</filename>
	<path>/uhk.fim.relayml/image_638096484630082517.bmp</path>
	<source>
		<database>Unspecified</database>
	</source>
	<size>
		<width>1388</width>
		<height>1038</height>
		<depth>3</depth>
	</size>
	<object>
		<name>logo</name>
		<pose>Unspecified</pose>
		<truncated>0</truncated>
		<difficult>0</difficult>
		<bndbox>
			<xmin>75</xmin>
			<ymin>566</ymin>
			<xmax>142</xmax>
			<ymax>675</ymax>
		</bndbox>
	</object>
	<object>
		<name>logo</name>
		<pose>Unspecified</pose>
		<truncated>0</truncated>
		<difficult>0</difficult>
		<bndbox>
			<xmin>1086</xmin>
			<ymin>580</ymin>
			<xmax>1153</xmax>
			<ymax>691</ymax>
		</bndbox>
	</object>
</annotation>