<annotation>
	<folder>uhk.fim.relayml</folder>
	<filename>image_638096487790716369.bmp</filename>
	<path>/uhk.fim.relayml/image_638096487790716369.bmp</path>
	<source>
		<database>Unspecified</database>
	</source>
	<size>
		<width>1388</width>
		<height>1038</height>
		<depth>3</depth>
	</size>
	<object>
		<name>logo</name>
		<pose>Unspecified</pose>
		<truncated>0</truncated>
		<difficult>0</difficult>
		<bndbox>
			<xmin>74</xmin>
			<ymin>565</ymin>
			<xmax>142</xmax>
			<ymax>674</ymax>
		</bndbox>
	</object>
	<object>
		<name>logo</name>
		<pose>Unspecified</pose>
		<truncated>0</truncated>
		<difficult>0</difficult>
		<bndbox>
			<xmin>1080</xmin>
			<ymin>582</ymin>
			<xmax>1148</xmax>
			<ymax>693</ymax>
		</bndbox>
	</object>
</annotation>